flaxlib-0.0.1a1.dist-info/METADATA
flaxlib-0.0.1a1.dist-info/WHEEL
flaxlib/flaxlib.pyi
flaxlib/__init__.py
flaxlib/flaxlib.cp310-win32.pyd
flaxlib-0.0.1a1.dist-info/RECORD
